Workbook
Name Beta: '[1]Simplification>'!$C$5
Name Cost_Of_debt: '[1]Simplify using Name'!$C$9
Name Cost_Of_equity: '[1]Simplify using Name'!$C$7
Name CostofDebt: '[1]Simplification>'!$C$6
Name Current_Sales: '[1]Simplify using Name'!$G$8
Name Debt_Funding: '[1]Simplify using Name'!$C$16
Name Debt_Value: '[1]Simplify using Name'!$C$14
Name DebtValue: '[1]Simplification>'!$C$9
Name Equity_Funding: '[1]Simplify using Name'!$C$15
Name Equity_Value: '[1]Simplify using Name'!$C$13
Name EquityValue: '[1]Simplification>'!$C$8
Name Gross_Margin: '[1]Simplify using Name'!$G$10
Name MarketReturn: '[1]Simplification>'!$C$4
Name Post_Tax_Cost_of_Debt: '[1]Simplify using Name'!$C$11
Name Riskfreerate: '[1]Simplification>'!$C$3
Name Sales_Growth: '[1]Simplify using Name'!$G$9
Name Taper_rate: Sheet1!$C$22
Name Tax_rate: Sheet1!$C$27
Name TAXRate: '[1]Simplification>'!$C$7
Name UPDATE: 'Data Sheet'!$E$1

Sheet Sheet1
B2: Discounted Cashflow Model
B3: Financial Modelling Course
B6: Company Overview
B7: Reliance Industries Limited is a Fortune 500 Indian multinational conglomerate headquartered in Mumbai, Maharashtra, and led by chairman Mukesh Ambani
B8: Oil-to-Chemicals (O2C): Includes hydrocarbon exploration, petroleum refining (such as the massive Jamnagar refinery complex), and petrochemical production.
B9: Digital Services (Jio): Provides widespread telecom, 5G, and digital services that transformed India's connectivity landscape.
B10: Retail (Reliance Retail): Operates as India's largest retailer across grocery, consumer electronics, and fashion.
B11: New Energy: Focuses on green energy infrastructure, manufacturing ecosystems, and sustainable technologies.
B13: As of the 2026 financial year-end, Reliance Industries reports a total employee headcount of 4,19,911 people at the group level.
B16: Key Assumption And Methodology
B17: Parameter
B18: Valuation Date | C18: 46291
B19: Projection Period
B21: Annual Growth Tapering | C21: 0.12
C22: 0.025
B23: Terminal Growth Rate | C23: 0.06
B25: Risk Free Rate (RF) | C25: 0.0711
B26: EquityRisk Premium (ERP) | C26: 0.06
B27: Tax Rate | C27: 0.25
B30: Income Statement
B32: Particulars | C32: 44286 | D32: 44651 | E32: 45016 | F32: 45382 | G32: 45747 | H32: 46112 | I32: CAGR
B33: Sales | C33: ='Data Sheet'!F17 -> 466307 | D33: ='Data Sheet'!G17 -> 694673 | E33: ='Data Sheet'!H17 -> 876396 | F33: ='Data Sheet'!I17 -> 899041 | G33: ='Data Sheet'!J17 -> 962820 | H33: ='Data Sheet'!K17 -> 1055780
B34: % Of growth | D34: =D33/C33-1 -> 0.48973316 | E34: =E33/D33-1 -> 0.26159502 | F34: =F33/E33-1 -> 0.025838776 | G34: =G33/F33-1 -> 0.070941147 | H34: =H33/G33-1 -> 0.096549719 | I34: =_xlfn.RRI(5,C33,H33) -> 0.17755256
B35: COGS | C35: =SUM('Data Sheet'!F18,'Data Sheet'!F19,'Data Sheet'!F20:F21) -> 331730 | D35: =SUM('Data Sheet'!G18,'Data Sheet'!G19,'Data Sheet'!G20:G21) -> 545982 | E35: =SUM('Data Sheet'!H18,'Data Sheet'!H19,'Data Sheet'!H20:H21) -> 693729 | F35: =SUM('Data Sheet'!I18,'Data Sheet'!I19,'Data Sheet'!I20:I21) -> 635522 | G35: =SUM('Data Sheet'!J18,'Data Sheet'!J19,'Data Sheet'!J20:J21) -> 702118 | H35: =SUM('Data Sheet'!K18,'Data Sheet'!K19,'Data Sheet'!K20:K21) -> 752428
B36: % of Revenue | D36: =D35/C35-1 -> 0.6458626 | E36: =E35/D35-1 -> 0.27060782 | F36: =F35/E35-1 -> -0.083904522 | G36: =G35/F35-1 -> 0.10478945 | H36: =H35/G35-1 -> 0.071654622
B37: Gross Profit | C37: =C33-C35 -> 134577 | D37: =D33-D35 -> 148691 | E37: =E33-E35 -> 182667 | F37: =F33-F35 -> 263519 | G37: =G33-G35 -> 260702 | H37: =H33-H35 -> 303352
B38: % Margin | C38: =C37/C33 -> 0.28860172 | D38: =D37/D33 -> 0.21404459 | E38: =E37/E33 -> 0.20842975 | F38: =F37/F33 -> 0.29311122 | G38: =G37/G33 -> 0.2707692 | H38: =H37/H33 -> 0.28732501
B39: Operating Expenses | C39: =SUM('Data Sheet'!F22:F24) -> 71915 | D39: =SUM('Data Sheet'!G22:G24) -> 83024 | E39: =SUM('Data Sheet'!H22:H24) -> 100875 | F39: =SUM('Data Sheet'!I22:I24) -> 110787 | G39: =SUM('Data Sheet'!J22:J24) -> 125352 | H39: =SUM('Data Sheet'!K22:K24) -> 144821
B40: % Revenue | C40: =C39/C33 -> 0.15422243 | D40: =D39/D33 -> 0.11951523 | E40: =E39/E33 -> 0.11510208 | F40: =F39/F33 -> 0.12322797 | G40: =G39/G33 -> 0.13019256 | H40: =H39/H33 -> 0.13716968
B41: EBITDA | C41: =C37-C39 -> 62662 | D41: =D37-D39 -> 65667 | E41: =E37-E39 -> 81792 | F41: =F37-F39 -> 152732 | G41: =G37-G39 -> 135350 | H41: =H37-H39 -> 158531
B42: % Margin | C42: =C41/C33 -> 0.13437928 | D42: =D41/D33 -> 0.094529368 | E42: =E41/E33 -> 0.093327674 | F42: =F41/F33 -> 0.16988324 | G42: =G41/G33 -> 0.14057664 | H42: =H41/H33 -> 0.15015534
B43: Depreciation | C43: ='Data Sheet'!F26 -> 26572 | D43: ='Data Sheet'!G26 -> 29782 | E43: ='Data Sheet'!H26 -> 40303 | F43: ='Data Sheet'!I26 -> 50832 | G43: ='Data Sheet'!J26 -> 53136 | H43: ='Data Sheet'!K26 -> 57688
B44: % Of Sales | C44: =C43/C33 -> 0.056983918 | D44: =D43/D33 -> 0.04287197 | E44: =E43/E33 -> 0.045987202 | F44: =F43/F33 -> 0.056540247 | G44: =G43/G33 -> 0.055187886 | H44: =H43/H33 -> 0.054640171
B45: EBIT | C45: =C41-C43 -> 36090 | D45: =D41-D43 -> 35885 | E45: =E41-E43 -> 41489 | F45: =F41-F43 -> 101900 | G45: =G41-G43 -> 82214 | H45: =H41-H43 -> 100843
B46: % Margin | C46: =C45/C33 -> 0.077395364 | D46: =D45/D33 -> 0.051657399 | E46: =E45/E33 -> 0.047340472 | F46: =F45/F33 -> 0.113343 | G46: =G45/G33 -> 0.085388754 | H46: =H45/H33 -> 0.095515164
B47: Other Income | C47: ='Data Sheet'!F25 -> 22432 | D47: ='Data Sheet'!G25 -> 19600 | E47: ='Data Sheet'!H25 -> 12020 | F47: ='Data Sheet'!I25 -> 15792 | G47: ='Data Sheet'!J25 -> 17824 | H47: ='Data Sheet'!K25 -> 28846
B48: Interest | C48: ='Data Sheet'!F27 -> 21189 | D48: ='Data Sheet'!G27 -> 14584 | E48: ='Data Sheet'!H27 -> 19571 | F48: ='Data Sheet'!I27 -> 23118 | G48: ='Data Sheet'!J27 -> 24269 | H48: ='Data Sheet'!K27 -> 27061
B49: % debt | C49: =C48/'Data Sheet'!F59 -> 0.075956582 | D49: =D48/'Data Sheet'!G59 -> 0.045695236 | E49: =E48/'Data Sheet'!H59 -> 0.043330883 | F49: =F48/'Data Sheet'!I59 -> 0.065916018 | G49: =G48/'Data Sheet'!J59 -> 0.064836113 | H49: =H48/'Data Sheet'!K59 -> 0.067155216
B50: Profit Before Tax | C50: =C45+C47-C48 -> 37333 | D50: =D45+D47-D48 -> 40901 | E50: =E45+E47-E48 -> 33938 | F50: =F45+F47-F48 -> 94574 | G50: =G45+G47-G48 -> 75769 | H50: =H45+H47-H48 -> 102628
B51: % of Revenue | C51: =C50/C33 -> 0.08006099 | D51: =D50/D33 -> 0.058878062 | E51: =E50/E33 -> 0.038724504 | F51: =F50/F33 -> 0.10519431 | G51: =G50/G33 -> 0.078694875 | H51: =H50/H33 -> 0.097205857
B52: Tax | C52: ='Data Sheet'!F29 -> 1722 | D52: ='Data Sheet'!G29 -> 15970 | E52: ='Data Sheet'!H29 -> 20376 | F52: ='Data Sheet'!I29 -> 25707 | G52: ='Data Sheet'!J29 -> 25230 | H52: ='Data Sheet'!K29 -> 27552
B53: % of PBT | C53: =C52/C50 -> 0.046125412 | D53: =D52/D50 -> 0.390455 | E53: =E52/E50 -> 0.60038894 | F53: =F52/F50 -> 0.27181889 | G53: =G52/G50 -> 0.33298579 | H53: =H52/H50 -> 0.26846475
B54: Net Profit | C54: =C50-C52 -> 35611 | D54: =D50-D52 -> 24931 | E54: =E50-E52 -> 13562 | F54: =F50-F52 -> 68867 | G54: =G50-G52 -> 50539 | H54: =H50-H52 -> 75076
B55: % of revenue | C55: =C54/C33 -> 0.076368144 | D55: =D54/D33 -> 0.035888828 | E55: =E54/E33 -> 0.01547474 | F55: =F54/F33 -> 0.076600511 | G55: =G54/G33 -> 0.052490601 | H55: =H54/H33 -> 0.071109511
B58: Balance Sheet
B59: Particulars | C59: 44286 | D59: 44651 | E59: 45016 | F59: 45382 | G59: 45747 | H59: 46112
B60: Equity Share Captal | C60: ='Data Sheet'!F57 -> 6445 | D60: ='Data Sheet'!G57 -> 6765 | E60: ='Data Sheet'!H57 -> 6766 | F60: ='Data Sheet'!I57 -> 6766 | G60: ='Data Sheet'!J57 -> 13532 | H60: ='Data Sheet'!K57 -> 13532
B61: Reserves | C61: ='Data Sheet'!F58 -> 693727 | D61: ='Data Sheet'!G58 -> 772720 | E61: ='Data Sheet'!H58 -> 709106 | F61: ='Data Sheet'!I58 -> 786715 | G61: ='Data Sheet'!J58 -> 829668 | H61: ='Data Sheet'!K58 -> 890498
B62: Borrowings | C62: ='Data Sheet'!F59 -> 278962 | D62: ='Data Sheet'!G59 -> 319158 | E62: ='Data Sheet'!H59 -> 451664 | F62: ='Data Sheet'!I59 -> 350719 | G62: ='Data Sheet'!J59 -> 374313 | H62: ='Data Sheet'!K59 -> 402962
B63: Other Liabilities | C63: ='Data Sheet'!F60 -> 340931 | D63: ='Data Sheet'!G60 -> 399979 | E63: ='Data Sheet'!H60 -> 438346 | F63: ='Data Sheet'!I60 -> 610848 | G63: ='Data Sheet'!J60 -> 732200 | H63: ='Data Sheet'!K60 -> 870554
B64: Total | C64: =SUM(C60:C63) -> 1320065 | D64: =SUM(D60:D63) -> 1498622 | E64: =SUM(E60:E63) -> 1605882 | F64: =SUM(F60:F63) -> 1755048 | G64: =SUM(G60:G63) -> 1949713 | H64: =SUM(H60:H63) -> 2177546
B65: Net Block | C65: ='Data Sheet'!F62 -> 541258 | D65: ='Data Sheet'!G62 -> 627798 | E65: ='Data Sheet'!H62 -> 724805 | F65: ='Data Sheet'!I62 -> 779985 | G65: ='Data Sheet'!J62 -> 999393 | H65: ='Data Sheet'!K62 -> 1124795
B66: Capital Work in Progress | C66: ='Data Sheet'!F63 -> 125953 | D66: ='Data Sheet'!G63 -> 172506 | E66: ='Data Sheet'!H63 -> 293752 | F66: ='Data Sheet'!I63 -> 338855 | G66: ='Data Sheet'!J63 -> 262358 | H66: ='Data Sheet'!K63 -> 237686
B67: Investments | C67: ='Data Sheet'!F64 -> 364828 | D67: ='Data Sheet'!G64 -> 394264 | E67: ='Data Sheet'!H64 -> 235560 | F67: ='Data Sheet'!I64 -> 225672 | G67: ='Data Sheet'!J64 -> 242381 | H67: ='Data Sheet'!K64 -> 248332
B68: Receivables | C68: ='Data Sheet'!F67 -> 19014 | D68: ='Data Sheet'!G67 -> 23640 | E68: ='Data Sheet'!H67 -> 28448 | F68: ='Data Sheet'!I67 -> 31628 | G68: ='Data Sheet'!J67 -> 42121 | H68: ='Data Sheet'!K67 -> 58491
B69: Inventory | C69: ='Data Sheet'!F68 -> 81672 | D69: ='Data Sheet'!G68 -> 107778 | E69: ='Data Sheet'!H68 -> 140008 | F69: ='Data Sheet'!I68 -> 152770 | G69: ='Data Sheet'!J68 -> 146062 | H69: ='Data Sheet'!K68 -> 166941
B70: Cash & Bank | C70: ='Data Sheet'!F69 -> 17397 | D70: ='Data Sheet'!G69 -> 36178 | E70: ='Data Sheet'!H69 -> 68664 | F70: ='Data Sheet'!I69 -> 97225 | G70: ='Data Sheet'!J69 -> 106502 | H70: ='Data Sheet'!K69 -> 145977
B71: Other Assets | C71: ='Data Sheet'!F65-SUM('Data Sheet'!F67:F69) -> 169943 | D71: ='Data Sheet'!G65-SUM('Data Sheet'!G67:G69) -> 136458 | E71: ='Data Sheet'!H65-SUM('Data Sheet'!H67:H69) -> 114645 | F71: ='Data Sheet'!I65-SUM('Data Sheet'!I67:I69) -> 128913 | G71: ='Data Sheet'!J65-SUM('Data Sheet'!J67:J69) -> 150896 | H71: ='Data Sheet'!K65-SUM('Data Sheet'!K67:K69) -> 195324
B72: Total | C72: =SUM(C65:C71) -> 1320065 | D72: =SUM(D65:D71) -> 1498622 | E72: =SUM(E65:E71) -> 1605882 | F72: =SUM(F65:F71) -> 1755048 | G72: =SUM(G65:G71) -> 1949713 | H72: =SUM(H65:H71) -> 2177546
B75: Revenue Projections And Growth Assumptions
B76: Year | C76: FY 2027 | D76: FY 2028 | E76: FY 2029 | F76: FY 2030 | G76: FY 2031 | H76: FY 2032
B77: Revenue Growth% | C77: {=CHOOSE(D79,C80:H80,C81:H81,C82:H82)} -> 0.12 | D77: 0.095 | E77: 0.07 | F77: 0.045 | G77: 0.02 | H77: -0.005
B78: Revenue in (Crs) | C78: =H33*(1+C77) -> 1182473.6 | D78: =C78*(1+D77) -> 1294808.6 | E78: =D78*(1+E77) -> 1385445.2 | F78: =E78*(1+F77) -> 1447790.2 | G78: =F78*(1+G77) -> 1476746 | H78: =G78*(1+H77) -> 1469362.3
B79: Chosen Scenarios | C79: Base Case | D79: =MATCH(C79,B80:B82,0) -> 1
B80: Base Case | C80: =C21 -> 0.12 | D80: =C80-Taper_rate -> 0.095 | E80: =D80-Taper_rate -> 0.07 | F80: =E80-Taper_rate -> 0.045 | G80: =F80-Taper_rate -> 0.02 | H80: =G80-Taper_rate -> -0.005
B81: Best Case | C81: =C80+5% -> 0.17 | D81: =C81-Taper_rate -> 0.145 | E81: =D81-Taper_rate -> 0.12 | F81: =E81-Taper_rate -> 0.095 | G81: =F81-Taper_rate -> 0.07 | H81: =G81-Taper_rate -> 0.045
B82: Worst Case | C82: =C80-5% -> 0.07 | D82: =C82-Taper_rate -> 0.045 | E82: =D82-Taper_rate -> 0.02 | F82: =E82-Taper_rate -> -0.005 | G82: =F82-Taper_rate -> -0.03 | H82: =G82-Taper_rate -> -0.055
B85: Free Cash flow Projection (Rs Crs)
C86: FY 2027 | D86: FY 2028 | E86: FY 2029 | F86: FY 2030 | G86: FY 2031 | H86: FY 2032
B87: Revenue | C87: =C78 -> 1182473.6 | D87: =D78 -> 1294808.6 | E87: =E78 -> 1385445.2 | F87: =F78 -> 1447790.2 | G87: =G78 -> 1476746 | H87: =H78 -> 1469362.3
B88: EBITDA Margin% | C88: =H42 -> 0.15015534 | D88: =C88 -> 0.15015534 | E88: =D88 -> 0.15015534 | F88: =E88 -> 0.15015534 | G88: =F88 -> 0.15015534 | H88: =G88 -> 0.15015534
B89: EBITDA | C89: =C87*C88 -> 177554.72 | D89: =D87*D88 -> 194422.42 | E89: =E87*E88 -> 208031.99 | F89: =F87*F88 -> 217393.43 | G89: =G87*G88 -> 221741.3 | H89: =H87*H88 -> 220632.59
B90: Less Depreciation | C90: =C87*AVERAGE($C$44:$H$44) -> 61530.289 | D90: =D87*AVERAGE($C$44:$H$44) -> 67375.666 | E90: =E87*AVERAGE($C$44:$H$44) -> 72091.963 | F90: =F87*AVERAGE($C$44:$H$44) -> 75336.101 | G90: =G87*AVERAGE($C$44:$H$44) -> 76842.823 | H90: =H87*AVERAGE($C$44:$H$44) -> 76458.609
B91: EBIT | C91: =C89-C90 -> 116024.43 | D91: =D89-D90 -> 127046.75 | E91: =E89-E90 -> 135940.03 | F91: =F89-F90 -> 142057.33 | G91: =G89-G90 -> 144898.47 | H91: =H89-H90 -> 144173.98
B92: Less Tax | C92: =C91*Tax_rate -> 29006.108 | D92: =D91*Tax_rate -> 31761.688 | E92: =E91*Tax_rate -> 33985.006 | F92: =F91*Tax_rate -> 35514.332 | G92: =G91*Tax_rate -> 36224.618 | H92: =H91*Tax_rate -> 36043.495
B93: NOPAT | C93: =C91-C92 -> 87018.324 | D93: =D91-D92 -> 95285.064 | E93: =E91-E92 -> 101955.02 | F93: =F91-F92 -> 106542.99 | G93: =G91-G92 -> 108673.85 | H93: =H91-H92 -> 108130.49
B94: Add: Depreciation | C94: =C90 -> 61530.289 | D94: =D90 -> 67375.666 | E94: =E90 -> 72091.963 | F94: =F90 -> 75336.101 | G94: =G90 -> 76842.823 | H94: =H90 -> 76458.609
B95: Less: Reinvestment | C95: =C93*-50% -> -43509.162 | D95: =D93*-50% -> -47642.532 | E95: =E93*-50% -> -50977.509 | F95: =F93*-50% -> -53271.497 | G95: =G93*-50% -> -54336.927 | H95: =H93*-50% -> -54065.243
B96: Free Cash flow to firm | C96: =SUM(C93:C95) -> 105039.45 | D96: =SUM(D93:D95) -> 115018.2 | E96: =SUM(E93:E95) -> 123069.47 | F96: =SUM(F93:F95) -> 128607.6 | G96: =SUM(G93:G95) -> 131179.75 | H96: =SUM(H93:H95) -> 130523.85
B99: WACC Calculation
B101: Target Capital Structure
B102: Proportion Of Debt | H102: =Comps!F20 -> 0.21421794
B103: Proportion Of Equity | H103: =1-H102 -> 0.78578206
B104: Current Capital Structure
B105: Market Cap | H105: =Comps!D5 -> 1659089
B106: Tota Debt | H106: =Comps!E5 -> 313923
B107: Debt/Equity | H107: =H106/H105 -> 0.18921408
B108: Cost Of Debt
B109: Pre-tax cost of debt | H109: 0.07
B110: tax Rate | H110: =Tax_rate -> 0.25
B111: After Tax Cost of Debt | H111: =H109*(1-H110) -> 0.0525
B112: Cost Of Equity
B113: Risk Free Rate | H113: =C25 -> 0.0711
B114: Equity Risk Premium | H114: =C26 -> 0.06
B115: Levered Equity Beta | H115: =Comps!I21*(1+Sheet1!H107*(1-Tax_rate)) -> 0.66502073
B116: Cost Of Equity | H116: =H113+H114*H115 -> 0.11100124
B117: WACC | H117: =(H116*H103)+(H111*H102) -> 0.098469228
B120: Terminal Value
B122: Terminal Year FCF (Fy32) | H122: =H96 -> 130523.85
B123: Terminal Growth Rate | H123: =C23 -> 0.06
...

Sheet Data Sheet
A1: COMPANY NAME | B1: RELIANCE INDUSTRIES LTD | E1: =IF(B2<>B3, "A NEW VERSION OF THE WORKSHEET IS AVAILABLE", "")
A2: LATEST VERSION | B2: 2.1 | E2: PLEASE DO NOT MAKE ANY CHANGES TO THIS SHEET
A3: CURRENT VERSION | B3: 2.1
B4: ='Data Sheet'!B1&" -" -> RELIANCE INDUSTRIES LTD -
A5: META
A6: Number of shares | B6: =IF(B9>0, B9/B8, 0) -> 1353.2535
A7: Face Value | B7: 10
A8: Current Price | B8: 1226 | C8: =IFERROR('Data Sheet'!C18,'Data Sheet'!C20:C22)*-1 -> -276076
A9: Market Capitalization | B9: 1659088.8
A15: PROFIT & LOSS
A16: Report Date | B16: 42825 | C16: 43190 | D16: 43555 | E16: 43921 | F16: 44286 | G16: 44651 | H16: 45016 | I16: 45382 | J16: 45747 | K16: 46112
A17: Sales | B17: 303954 | C17: 390823 | D17: 568337 | E17: 596679 | F17: 466307 | G17: 694673 | H17: 876396 | I17: 899041 | J17: 962820 | K17: 1055780
A18: Raw Material Cost | B18: 217518 | C18: 276076 | D18: 399167 | E18: 410288 | F18: 301765 | G18: 494449 | H18: 618746 | I18: 590226 | J18: 644813 | K18: 698930
A19: Change in Inventory | B19: 5218 | C19: 8610 | D19: 4680 | E19: 5048 | F19: 9064 | G19: 21457 | H19: 30263 | I19: 4883 | J19: 15124 | K19: 10267
A20: Power and Fuel | B20: 11251 | C20: 14569 | D20: 17029 | E20: 15098 | F20: 13214 | G20: 17902 | H20: 25062 | I20: 22137 | J20: 23823 | K20: 22069
A21: Other Mfr. Exp | B21: 9909 | C21: 9691 | D21: 12198 | E21: 11434 | F21: 7687 | G21: 12174 | H21: 19658 | I21: 18276 | J21: 18358 | K21: 21162
A22: Employee Cost | B22: 8388 | C22: 9523 | D22: 12488 | E22: 14075 | F22: 14817 | G22: 18758 | H22: 24872 | I22: 25679 | J22: 28559 | K22: 30318
A23: Selling and admin | B23: 18520 | C23: 29111 | D23: 50221 | E23: 62622 | F23: 56154 | G23: 63513 | H23: 67369 | I23: 77292 | J23: 88760 | K23: 104723
A24: Other Expenses | B24: -2721 | C24: -3852 | D24: -2336 | E24: -1056 | F24: 944 | G24: 753 | H24: 8634 | I24: 7816 | J24: 8033 | K24: 9780
A25: Other Income | B25: 9222 | C25: 9869 | D25: 8406 | E25: 8570 | F25: 22432 | G25: 19600 | H25: 12020 | I25: 15792 | J25: 17824 | K25: 28846
A26: Depreciation | B26: 11646 | C26: 16706 | D26: 20934 | E26: 22203 | F26: 26572 | G26: 29782 | H26: 40303 | I26: 50832 | J26: 53136 | K26: 57688
A27: Interest | B27: 3849 | C27: 8052 | D27: 16495 | E27: 22027 | F27: 21189 | G27: 14584 | H27: 19571 | I27: 23118 | J27: 24269 | K27: 27061
... A31: Dividend Amount | B31: 3254.9 | C31: 3553.2 | D31: 3851.9 | E31: 4120.35 | F31: 4511.5 | G31: 5412 | H31: 6089.4 | I31: 6766 | J31: 7442.6 | K31: 8119.2
A40: Quarters
A41: Report Date | B41: 45382 | C41: 45473 | D41: 45565 | E41: 45657 | F41: 45747 | G41: 45838 | H41: 45930 | I41: 46022 | J41: 46112 | K41: 46203
A42: Sales | B42: 236533 | C42: 231784 | D42: 231535 | E42: 239986 | F42: 261388 | G42: 243632 | H42: 254623 | I42: 264905 | J42: 294059 | K42: 309468
A43: Expenses | B43: 194017 | C43: 193019 | D43: 192477 | E43: 196197 | F43: 217556 | G43: 200727 | H43: 208738 | I43: 218887 | J43: 249918 | K43: 261951
A44: Other Income | B44: 4534 | C44: 3983 | D44: 4876 | E44: 4214 | F44: 4905 | G44: 15119 | H44: 4482 | I44: 4914 | J44: 4447 | K44: 6550
A45: Depreciation | B45: 13569 | C45: 13596 | D45: 12880 | E45: 13181 | F45: 13479 | G45: 13842 | H45: 14416 | I45: 14622 | J45: 14808 | K45: 15100
A46: Interest | B46: 5761 | C46: 5918 | D46: 6017 | E46: 6179 | F46: 6155 | G46: 7036 | H46: 6827 | I46: 6613 | J46: 6585 | K46: 8337
A47: Profit before tax | B47: 27720 | C47: 23234 | D47: 25037 | E47: 28643 | F47: 29103 | G47: 37146 | H47: 29124 | I47: 29697 | J47: 27195 | K47: 30630
A48: Tax | B48: 6577 | C48: 5786 | D48: 5936 | E48: 6839 | F48: 6669 | G48: 6465 | H48: 6978 | I48: 7530 | J48: 6579 | K48: 7629
A49: Net profit | B49: 18951 | C49: 15138 | D49: 16563 | E49: 18540 | F49: 19407 | G49: 26994 | H49: 18165 | I49: 18645 | J49: 16971 | K49: 20946
A50: Operating Profit | B50: 42516 | C50: 38765 | D50: 39058 | E50: 43789 | F50: 43832 | G50: 42905 | H50: 45885 | I50: 46018 | J50: 44141 | K50: 47517
A51: EBITDA | B51: 16892.02 | C51: 20164.6 | D51: 19850 | E51: 20404 | F51: 22268 | G51: 23828 | H51: 22359 | I51: 18164 | J51: 17822 | K51: 22113
A55: BALANCE SHEET
A56: Report Date | B56: 42825 | C56: 43190 | D56: 43555 | E56: 43921 | F56: 44286 | G56: 44651 | H56: 45016 | I56: 45382 | J56: 45747 | K56: 46112
A57: Equity Share Capital | B57: 2959 | C57: 5922 | D57: 5926 | E57: 6339 | F57: 6445 | G57: 6765 | H57: 6766 | I57: 6766 | J57: 13532 | K57: 13532
A58: Reserves | B58: 260750 | C58: 287584 | D58: 381186 | E58: 442827 | F58: 693727 | G58: 772720 | H58: 709106 | I58: 786715 | J58: 829668 | K58: 890498
A59: Borrowings | B59: 217475 | C59: 239843 | D59: 307714 | E59: 355133 | F59: 278962 | G59: 319158 | H59: 451664 | I59: 350719 | J59: 374313 | K59: 402962
A60: Other Liabilities | B60: 225618 | C60: 277924 | D60: 302804 | E60: 358716 | F60: 340931 | G60: 399979 | H60: 438346 | I60: 610848 | J60: 732200 | K60: 870554
A61: Total | B61: 706802 | C61: 811273 | D61: 997630 | E61: 1163015 | F61: 1320065 | G61: 1498622 | H61: 1605882 | I61: 1755048 | J61: 1949713 | K61: 2177546
A62: Net Block | B62: 198526 | C62: 403885 | D62: 398374 | E62: 532658 | F62: 541258 | G62: 627798 | H62: 724805 | I62: 779985 | J62: 999393 | K62: 1124795
A63: Capital Work in Progress | B63: 324837 | C63: 187022 | D63: 179463 | E63: 109106 | F63: 125953 | G63: 172506 | H63: 293752 | I63: 338855 | J63: 262358 | K63: 237686
A64: Investments | B64: 82899 | C64: 82862 | D64: 235635 | E64: 276767 | F64: 364828 | G64: 394264 | H64: 235560 | I64: 225672 | J64: 242381 | K64: 248332
A65: Other Assets | B65: 100540 | C65: 137504 | D65: 184158 | E65: 244484 | F65: 288026 | G65: 304054 | H65: 351765 | I65: 410536 | J65: 445581 | K65: 566733
A66: Total | B66: 706802 | C66: 811273 | D66: 997630 | E66: 1163015 | F66: 1320065 | G66: 1498622 | H66: 1605882 | I66: 1755048 | J66: 1949713 | K66: 2177546
A67: Receivables | B67: 8177 | C67: 17555 | D67: 30089 | E67: 19656 | F67: 19014 | G67: 23640 | H67: 28448 | I67: 31628 | J67: 42121 | K67: 58491
... A70: No. of Equity Shares | B70: 2958924277 | C70: 5921826196 | D70: 5925868997 | E70: 6338693823 | F70: 6762068814 | G70: 6765994014 | H70: 6766094014 | I70: 6766094014 | J70: 13532515463 | K70: 13532472634
A71: New Bonus Shares | C71: 2959863235 | D71: 2959863235 | J71: 6766186449 | K71: 11955084287
A72: Face value | B72: 10 | C72: 10 | D72: 10 | E72: 10 | F72: 10 | G72: 10 | H72: 10 | I72: 10 | J72: 10 | K72: 10
A80: CASH FLOW:
A81: Report Date | B81: 42825 | C81: 43190 | D81: 43555 | E81: 43921 | F81: 44286 | G81: 44651 | H81: 45016 | I81: 45382 | J81: 45747 | K81: 46112
A82: Cash from Operating Activity | B82: 49550 | C82: 71459 | D82: 42346 | E82: 94877 | F82: 26958 | G82: 110654 | H82: 115032 | I82: 158788 | J82: 178703 | K82: 192113
A83: Cash from Investing Activity | B83: -66201 | C83: -68192 | D83: -94507 | E83: -72497 | F83: -142385 | G83: -109162 | H83: -93001 | I83: -113581 | J83: -137535 | K83: -101089
A84: Cash from Financing Activity | B84: 8617 | C84: -2001 | D84: 55906 | E84: -2541 | F84: 101904 | G84: 17289 | H84: 10455 | I84: -16646 | J84: -31891 | K84: -51549
A85: Net Cash Flow | B85: -8034 | C85: 1266 | D85: 3745 | E85: 19839 | F85: -13523 | G85: 18781 | H85: 32486 | I85: 28561 | J85: 9277 | K85: 39475
A90: PRICE: | B90: 300.09 | C90: 401.08 | D90: 619.43 | E90: 506.06 | F90: 918.78 | G90: 1208.51 | H90: 1069.21 | I90: 1485.85 | J90: 1275.1 | K90: 1343.9
A92: DERIVED:
A93: Adjusted Equity Shares in Cr | B93: 1387.22 | C93: 1351.39 | D93: 1352.26 | E93: 1352.37 | F93: 1267.89 | G93: 1352.98 | H93: 1353.12 | I93: 1353.14 | J93: 1353.24 | K93: 1353.25

Sheet Comps
B2: Comps Data
B4: Name | C4: CMP Rs. | D4: Mar Cap Rs.Cr. | E4: Debt Rs.Cr. | F4: Debt / Eq | G4: Sales Rs.Cr. | H4: Beta | I4: Cash and Equivalent
B5: Reliance Industries | C5: 1226 | D5: 1659089 | E5: 313923 | F5: 0.49 | G5: 309468 | H5: 1.15 | I5: 23196
B6: Bharti Airtel | C6: 1837 | D6: 1146380 | E6: 211854 | F6: 1.31 | G6: 58539 | H6: 0.92 | I6: 15204
B7: Indian Oil Corp (IOCL) | C7: 136 | D7: 191625 | E7: 141610 | F7: 0.81 | G7: 266407 | H7: 0.95 | I7: 12410
B8: Bharat Petroleum (BPCL) | C8: 308 | D8: 133842 | E8: 64815 | F8: 0.94 | G8: 151277 | H8: 0.89 | I8: 4213
B9: Tata Trent | C9: 2666 | D9: 142340 | E9: 684 | F9: 0.22 | G9: 4113 | H9: 1.21 | I9: 945
B12: Industry Beta
B14: Name | C14: Equit Value | D14: Total Debt | E14: Debt/Equity | F14: Debt /Capital | G14: Tax Rate % | H14: Levered Beta | I14: Unlivered Beta
B15: Reliance Industries | C15: =D5 -> 1659089 | D15: =E5 -> 313923 | E15: =D15/C15 -> 0.18921408 | F15: =D15/(C15+D15) -> 0.15910851 | G15: =Tax_rate -> 0.25 | H15: =H5 -> 1.15 | I15: =H15/(1+E15)*(1-G15) -> 0.72526891
B16: Bharti Airtel | C16: =D6 -> 1146380 | D16: =E6 -> 211854 | E16: =D16/C16 -> 0.1848026 | F16: =D16/(C16+D16) -> 0.15597754 | G16: =Tax_rate -> 0.25 | H16: =H6 -> 0.92 | I16: =H16/(1+E16)*(1-G16) -> 0.5823755
B17: Indian Oil Corp (IOCL) | C17: =D7 -> 191625 | D17: =E7 -> 141610 | E17: =D17/C17 -> 0.73899543 | F17: =D17/(C17+D17) -> 0.42495536 | G17: =Tax_rate -> 0.25 | H17: =H7 -> 0.95 | I17: =H17/(1+E17)*(1-G17) -> 0.4097193
B18: Bharat Petroleum (BPCL) | C18: =D8 -> 133842 | D18: =E8 -> 64815 | E18: =D18/C18 -> 0.48426503 | F18: =D18/(C18+D18) -> 0.32626588 | G18: =Tax_rate -> 0.25 | H18: =H8 -> 0.89 | I18: =H18/(1+E18)*(1-G18) -> 0.44971753
B19: Tata Trent | C19: =D9 -> 142340 | D19: =E9 -> 684 | E19: =D19/C19 -> 0.0048053955 | F19: =D19/(C19+D19) -> 0.0047824141 | G19: =Tax_rate -> 0.25 | H19: =H9 -> 1.21 | I19: =H19/(1+E19)*(1-G19) -> 0.90315996
B20: Average | E20: =AVERAGE(E15:E19) -> 0.32041651 | F20: =AVERAGE(F15:F19) -> 0.21421794 | G20: =AVERAGE(G15:G19) -> 0.25 | H20: =AVERAGE(H15:H19) -> 1.024 | I20: =AVERAGE(I15:I19) -> 0.61404824
B21: Median | E21: =MEDIAN(E15:E19) -> 0.18921408 | F21: =MEDIAN(F15:F19) -> 0.15910851 | G21: =MEDIAN(G15:G19) -> 0.25 | H21: =MEDIAN(H15:H19) -> 0.95 | I21: =MEDIAN(I15:I19) -> 0.5823755
